harmony/__init__.py
harmony/examples.py
harmony/matching/__init__.py
harmony/matching/affinity_propagation_clustering.py
harmony/matching/cluster.py
harmony/matching/default_matcher.py
harmony/matching/deterministic_clustering.py
harmony/matching/generate_cluster_topics.py
harmony/matching/generate_crosswalk_table.py
harmony/matching/generate_semantic_keywords.py
harmony/matching/hdbscan_clustering.py
harmony/matching/instrument_to_instrument_similarity.py
harmony/matching/kmeans_clustering.py
harmony/matching/matcher.py
harmony/matching/negator.py
harmony/matching/wmd_matcher.py
harmony/parsing/20240719_pdf_question_extraction_sklearn_crf_model.pkl
harmony/parsing/__init__.py
harmony/parsing/excel_parser.py
harmony/parsing/pdf_parser.py
harmony/parsing/text_parser.py
harmony/parsing/wrapper_all_parsers.py
harmony/parsing/util/__init__.py
harmony/parsing/util/excel_to_pandas.py
harmony/parsing/util/feature_extraction.py
harmony/parsing/util/tika_wrapper.py
harmony/schemas/__init__.py
harmony/schemas/catalogue_instrument.py
harmony/schemas/catalogue_question.py
harmony/schemas/text_vector.py
harmony/schemas/enums/__init__.py
harmony/schemas/enums/clustering_algorithms.py
harmony/schemas/enums/file_types.py
harmony/schemas/enums/languages.py
harmony/schemas/errors/__init__.py
harmony/schemas/errors/base.py
harmony/schemas/exceptions/__init__.py
harmony/schemas/exceptions/base.py
harmony/schemas/requests/__init__.py
harmony/schemas/requests/text.py
harmony/schemas/responses/__init__.py
harmony/schemas/responses/text.py
harmony/services/__init__.py
harmony/stopwords/ar
harmony/stopwords/az
harmony/stopwords/be
harmony/stopwords/bn
harmony/stopwords/ca
harmony/stopwords/da
harmony/stopwords/de
harmony/stopwords/el
harmony/stopwords/en
harmony/stopwords/es
harmony/stopwords/eu
harmony/stopwords/fi
harmony/stopwords/fr
harmony/stopwords/he
harmony/stopwords/hu
harmony/stopwords/id
harmony/stopwords/it
harmony/stopwords/kk
harmony/stopwords/ne
harmony/stopwords/nl
harmonydata-1.0.5.dist-info/licenses/LICENSE
harmonydata-1.0.5.dist-info/METADATA
harmonydata-1.0.5.dist-info/WHEEL
harmonydata-1.0.5.dist-info/top_level.txt
harmonydata-1.0.5.dist-info/RECORD
