Metadata-Version: 2.4
Name: harmonydata
Version: 1.0.5
Summary: Harmony Tool for Retrospective Data Harmonisation
Author-email: Thomas Wood <thomas@fastdatascience.com>
Maintainer-email: Thomas Wood <thomas@fastdatascience.com>
License: MIT License
Project-URL: Documentation, https://harmonydata.ac.uk/frequently-asked-questions/
Project-URL: Bug Reports, https://github.com/harmonydata/harmony/issues
Project-URL: Source Code, https://github.com/harmonydata/harmony
Keywords: harmony,harmonisation,harmonization,harmonise
Classifier: Development Status :: 5 - Production/Stable
Classifier: Intended Audience :: Developers
Classifier: Topic :: Software Development :: Build Tools
Classifier: Programming Language :: Python :: 3
Classifier: Programming Language :: Python :: 3.6
Classifier: Programming Language :: Python :: 3.7
Classifier: Programming Language :: Python :: 3.8
Classifier: Programming Language :: Python :: 3.9
Classifier: Programming Language :: Python :: 3.10
Classifier: Programming Language :: Python :: 3.11
Classifier: Programming Language :: Python :: 3.12
Classifier: Programming Language :: Python :: 3.13
Classifier: Programming Language :: Python :: 3 :: Only
Classifier: License :: OSI Approved :: MIT License
Classifier: Operating System :: OS Independent
Classifier: Topic :: Text Processing :: Linguistic
Classifier: Intended Audience :: Science/Research
Classifier: Intended Audience :: Healthcare Industry
Classifier: Intended Audience :: Information Technology
Classifier: Topic :: Scientific/Engineering :: Medical Science Apps.
Classifier: Topic :: Scientific/Engineering :: Artificial Intelligence
Classifier: Topic :: Sociology
Requires-Python: <=3.13.0,>=3.6
License-File: LICENSE
Requires-Dist: pydantic==2.8.2; python_version <= "3.13"
Requires-Dist: pandas==2.2.2; python_version <= "3.13"
Requires-Dist: tika==2.6.0; python_version <= "3.13"
Requires-Dist: lxml==5.3.0; python_version <= "3.13"
Requires-Dist: langdetect==1.0.9; python_version <= "3.13"
Requires-Dist: XlsxWriter==3.0.9; python_version <= "3.13"
Requires-Dist: openpyxl==3.1.2; python_version <= "3.13"
Requires-Dist: wget==3.2; python_version <= "3.13"
Requires-Dist: sentence-transformers==3.4.1; python_version <= "3.13"
Requires-Dist: numpy==1.26.4; python_version <= "3.13"
Requires-Dist: sklearn-crfsuite==0.5.0; python_version <= "3.13"
Requires-Dist: scikit-learn; python_version <= "3.13"
Requires-Dist: scipy==1.14.1; python_version <= "3.13"
Requires-Dist: huggingface-hub==0.29.3; python_version <= "3.13"
Provides-Extra: dev
Requires-Dist: check-manifest; extra == "dev"
Requires-Dist: pytest; extra == "dev"
Dynamic: license-file
